word_document_text_editor/__init__.py
word_document_text_editor/main.py
word_document_text_editor/tools.py
word_document_text_editor/utils.py
word_document_text_editor_mcp-1.0.2.dist-info/METADATA
word_document_text_editor_mcp-1.0.2.dist-info/WHEEL
word_document_text_editor_mcp-1.0.2.dist-info/entry_points.txt
word_document_text_editor_mcp-1.0.2.dist-info/top_level.txt
word_document_text_editor_mcp-1.0.2.dist-info/RECORD
