Metadata-Version: 2.4
Name: word-document-text-editor-mcp
Version: 1.0.2
Summary: Word文档文本编辑MCP服务 - 提供文档文本编辑相关功能
Author-email: Word MCP Services <support@example.com>
License: MIT
Requires-Python: >=3.10
Requires-Dist: python-docx>=1.1.0
Requires-Dist: fastmcp>=2.8.1
